setta/__init__.py
setta/server.py
setta/start.py
setta/cli/__init__.py
setta/cli/connect.py
setta/cli/logger.py
setta/code_gen/__init__.py
setta/code_gen/create_runnable_scripts.py
setta/code_gen/export_selected.py
setta/code_gen/find_placeholders.py
setta/code_gen/utils.py
setta/code_gen/python/__init__.py
setta/code_gen/python/ast_utils.py
setta/code_gen/python/check_scope.py
setta/code_gen/python/generate_code.py
setta/code_gen/python/make_parseable.py
setta/code_gen/python/position_line_col.py
setta/code_gen/python/validate_imports.py
setta/code_gen/yaml/__init__.py
setta/code_gen/yaml/generate_yaml.py
setta/code_gen/yaml/section_dict.py
setta/database/__init__.py
setta/database/backup.py
setta/database/db_init.py
setta/database/db_objs.py
setta/database/import_db.py
setta/database/seed.py
setta/database/settings_file.py
setta/database/utils.py
setta/database/db/__init__.py
setta/database/db/artifacts/__init__.py
setta/database/db/artifacts/load.py
setta/database/db/artifacts/save.py
setta/database/db/artifacts/save_or_create.py
setta/database/db/artifacts/utils.py
setta/database/db/codeInfo/__init__.py
setta/database/db/codeInfo/copy.py
setta/database/db/codeInfo/load.py
setta/database/db/codeInfo/save.py
setta/database/db/codeInfo/utils.py
setta/database/db/evRefs/__init__.py
setta/database/db/evRefs/load.py
setta/database/db/evRefs/save.py
setta/database/db/projects/__init__.py
setta/database/db/projects/copy.py
setta/database/db/projects/delete.py
setta/database/db/projects/load.py
setta/database/db/projects/save.py
setta/database/db/projects/saveAs.py
setta/database/db/projects/utils.py
setta/database/db/sectionVariants/__init__.py
setta/database/db/sectionVariants/copy.py
setta/database/db/sectionVariants/load.py
setta/database/db/sectionVariants/save.py
setta/database/db/sectionVariants/utils.py
setta/database/db/sections/__init__.py
setta/database/db/sections/copy.py
setta/database/db/sections/jsonSource.py
setta/database/db/sections/load.py
setta-0.0.17.dist-info/LICENSE
setta-0.0.17.dist-info/METADATA
setta-0.0.17.dist-info/WHEEL
setta-0.0.17.dist-info/entry_points.txt
setta-0.0.17.dist-info/top_level.txt
setta-0.0.17.dist-info/RECORD
