Metadata-Version: 2.2
Name: setta
Version: 0.0.17
Summary: Python without the donkeywork.
Home-page: https://setta.dev
Author: Kevin Musgrave, Jeff Musgrave
License: Apache-2.0
Project-URL: GitHub, https://github.com/settadev/setta
License-File: LICENSE
Requires-Dist: click>=8.1.8
Requires-Dist: requests>=2.32.3
Requires-Dist: PyYAML>=6.0.2
Requires-Dist: websockets>=15.0
Requires-Dist: fastapi>=0.115.8
Requires-Dist: uvicorn>=0.34.0
Requires-Dist: docstring_parser>=0.16
Requires-Dist: pywinpty>=2.0.15; platform_system == "Windows"
Requires-Dist: ptyprocess>=0.7.0; platform_system != "Windows"
Requires-Dist: psutil>=7.0.0
Requires-Dist: basedpyright>=1.27.1
Requires-Dist: docstring-to-markdown>=0.15
Requires-Dist: black>=23.7.0
Requires-Dist: watchdog>=6.0.0
Provides-Extra: dev
Requires-Dist: black==23.7.0; extra == "dev"
Requires-Dist: build==1.0.3; extra == "dev"
Requires-Dist: isort==5.12.0; extra == "dev"
Requires-Dist: flake8==6.1.0; extra == "dev"
